Workbook

Sheet 前提・出典
A1: 項目 | B1: 値 | C1: 備考
A2: 燃油サーチャージ率 | B2: 0.12 | C2: 2026-08-01発効12%（7/16〜7/31は11%）。全仕向地の基本送料に掛かる。出典: Orange Connex公式告知
A3: EU関税（事前徴収） | B3: 555 | C3: 円/関税分類番号(HSコード)。申告価値150ユーロ以下。出典: SpeedPAK Economy料金ガイド
A4: 関税処理手数料率 | B4: 0.021 | C4: 関税・税金等合計の2.1%（EU・米国共通）
A5: 米国輸入通関手数料 | B5: 245 | C5: 円/件。全ての米国向け貨物に適用
A6: 為替（参考換算用） | B6: 150 | C6: 円/米ドル。参考値（青字は変更可）
A8: ■料金基準: eBay SpeedPAK Economy（eBay注文用）。出典＝RATE GUIDE of eBay SpeedPAK Economy-JP.pdf（2026-07-30発効）p.6-7(米)/p.10(英)/p.13-14(EU27)/p.17(豪)。
A9: ■フォルダ内のExcel4本はOrange Connex (Multi-Channel) Ship via Economy（eBay以外の販路用・約1割高い）の料金表のため、本表では使用していない。
A10: ■イギリスも燃油サーチャージは基本送料に含まれず加算する（SpeedPAK料金ガイドp.10注記2）。※Multi-Channel版Excelのみ燃油込み表記だった。
A11: ■前提条件: 同一貨物（通常サイズ・繁忙期外・1商品=関税分類1つ）。
A12: ■アメリカは表の金額に加えて「推定米国関税（申告額×事前設定レート）＋その関税額の2.1%」が別途（率は非公表=Unknown、アメリカタブで想定計算可）。
A13: ■イギリス(£135以下)・オーストラリア(AUD1,000以下)のVAT/GSTはeBayがバイヤーから徴収するため送料側の負担なし。
A14: ■条件付き費用（通常は発生しない・表に含まず）: 米国 規定外寸法2,475円 / EU バルキー2,520円・繁忙期割増34円(11/1〜12/31) / 豪州 検疫・正式申告等。
A15: ■燃油率の告知: orangeconnex.jp ニュース（2026-07-15付=11%、2026-07-29付=12%）。2週間ごと更新。

Sheet 基礎データ
A1: 基本送料（円・燃油等含まず）。出典: eBay SpeedPAK Economy料金ガイドPDF（2026-07-30発効）
A2: 重量kg最大 | B2: US本土48州 | C2: イギリス | D2: オーストラリア | E2: DE | F2: AT | G2: BE | H2: BG | I2: CY | J2: CZ | K2: DK | L2: EE | M2: ES | N2: FI | O2: FR | P2: GR | Q2: HR | R2: HU | S2: IE | T2: IT | U2: LT | V2: LU | W2: LV | X2: MT | Y2: NL | Z2: PL | AA2: PT | AB2: RO | AC2: SE | AD2: SI | AE2: SK
A3: 0.1 | B3: 1157 | C3: 885 | D3: 1077 | E3: 1440 | F3: 1942 | G3: 2234 | H3: 1883 | I3: 3861 | J3: 2234 | K3: 2205 | L3: 2352 | M3: 1793 | N3: 2991 | O3: 1963 | P3: 1810 | Q3: 2264 | R3: 1810 | S3: 2071 | T3: 1996 | U3: 1712 | V3: 1979 | W3: 2032 | X3: 3015 | Y3: 2104 | Z3: 1610 | AA3: 1784 | AB3: 1738 | AC3: 1629 | AD3: 2217 | AE3: 2160
A4: 0.2 | B4: 1289 | C4: 1012 | D4: 1247 | E4: 1664 | F4: 2281 | G4: 2522 | H4: 2233 | I4: 4296 | J4: 2515 | K4: 2471 | L4: 2751 | M4: 2119 | N4: 3255 | O4: 2313 | P4: 2239 | Q4: 2613 | R4: 2158 | S4: 2411 | T4: 2319 | U4: 2119 | V4: 2254 | W4: 2437 | X4: 3579 | Y4: 2367 | Z4: 1957 | AA4: 2090 | AB4: 2084 | AC4: 1889 | AD4: 2569 | AE4: 2513
A5: 0.3 | B5: 1491 | C5: 1173 | D5: 1422 | E5: 1902 | F5: 2412 | G5: 2654 | H5: 2363 | I5: 4427 | J5: 2646 | K5: 2603 | L5: 2882 | M5: 2248 | N5: 3386 | O5: 2445 | P5: 2370 | Q5: 2741 | R5: 2289 | S5: 2541 | T5: 2449 | U5: 2248 | V5: 2384 | W5: 2567 | X5: 3710 | Y5: 2498 | Z5: 2088 | AA5: 2221 | AB5: 2214 | AC5: 2020 | AD5: 2699 | AE5: 2643
A6: 0.4 | B6: 1677 | C6: 1349 | D6: 1451 | E6: 2044 | F6: 2829 | G6: 2971 | H6: 2799 | I6: 5027 | J6: 2930 | K6: 2865 | L6: 3430 | M6: 2637 | N6: 3648 | O6: 2934 | P6: 2971 | Q6: 3180 | R6: 2728 | S6: 2963 | T6: 2838 | U6: 2792 | V6: 2691 | W6: 3113 | X6: 4569 | Y6: 2761 | Z6: 2520 | AA6: 2571 | AB6: 2654 | AC6: 2281 | AD6: 3137 | AE6: 3092
A7: 0.5 | B7: 1943 | C7: 1482 | D7: 1537 | E7: 2296 | F7: 3088 | G7: 3233 | H7: 3061 | I7: 5288 | J7: 3190 | K7: 3126 | L7: 3691 | M7: 2897 | N7: 3909 | O7: 3196 | P7: 3233 | Q7: 3442 | R7: 2988 | S7: 3224 | T7: 3098 | U7: 3053 | V7: 2952 | W7: 3374 | X7: 4829 | Y7: 3021 | Z7: 2781 | AA7: 2832 | AB7: 2916 | AC7: 2542 | AD7: 3396 | AE7: 3353
A8: 0.6 | B8: 2096 | C8: 1606 | D8: 1709 | E8: 2504 | F8: 3219 | G8: 3363 | H8: 3191 | I8: 5419 | J8: 3321 | K8: 3256 | L8: 3821 | M8: 3028 | N8: 4040 | O8: 3326 | P8: 3363 | Q8: 3572 | R8: 3120 | S8: 3353 | T8: 3229 | U8: 3182 | V8: 3080 | W8: 3504 | X8: 4961 | Y8: 3152 | Z8: 2911 | AA8: 2962 | AB8: 3046 | AC8: 2671 | AD8: 3527 | AE8: 3484
A9: 0.7 | B9: 2189 | C9: 1746 | D9: 1742 | E9: 2742 | F9: 3635 | G9: 3679 | H9: 3629 | I9: 6021 | J9: 3601 | K9: 3521 | L9: 4368 | M9: 3413 | N9: 4304 | O9: 3823 | P9: 3963 | Q9: 4012 | R9: 3557 | S9: 3775 | T9: 3617 | U9: 3729 | V9: 3386 | W9: 4046 | X9: 5826 | Y9: 3416 | Z9: 3341 | AA9: 3408 | AB9: 3485 | AC9: 3030 | AD9: 3965 | AE9: 3933
A10: 0.8 | B10: 2549 | C10: 1856 | D10: 1883 | E10: 3102 | F10: 3766 | G10: 3807 | H10: 3759 | I10: 6151 | J10: 3732 | K10: 3651 | L10: 4498 | M10: 3544 | N10: 4434 | O10: 3954 | P10: 4094 | Q10: 4142 | R10: 3688 | S10: 3905 | T10: 3747 | U10: 3858 | V10: 3516 | W10: 4177 | X10: 5955 | Y10: 3546 | Z10: 3472 | AA10: 3538 | AB10: 3615 | AC10: 3161 | AD10: 4096 | AE10: 4063
A11: 0.9 | B11: 2660 | C11: 2000 | D11: 1950 | E11: 3319 | F11: 4027 | G11: 4069 | H11: 4021 | I11: 6413 | J11: 3993 | K11: 3912 | L11: 4759 | M11: 3804 | N11: 4696 | O11: 4215 | P11: 4354 | Q11: 4403 | R11: 3947 | S11: 4167 | T11: 4009 | U11: 4120 | V11: 3776 | W11: 4438 | X11: 6217 | Y11: 3807 | Z11: 3733 | AA11: 3800 | AB11: 3877 | AC11: 3420 | AD11: 4356 | AE11: 4323
A12: 1 | B12: 2848 | C12: 2113 | D12: 1950 | E12: 3400 | F12: 4441 | G12: 4390 | H12: 4461 | I12: 7012 | J12: 4279 | K12: 4177 | L12: 5303 | M12: 4196 | N12: 4958 | O12: 4563 | P12: 4955 | Q12: 4842 | R12: 4386 | S12: 4587 | T12: 4396 | U12: 4664 | V12: 4063 | W12: 4984 | X12: 7079 | Y12: 4077 | Z12: 4168 | AA12: 4154 | AB12: 4315 | AC12: 3681 | AD12: 4796 | AE12: 4770
A13: 1.1 | B13: 2958 | C13: 2274 | D13: 2017 | E13: 3635 | F13: 4571 | G13: 4521 | H13: 4589 | I13: 7142 | J13: 4410 | K13: 4307 | L13: 5433 | M13: 4326 | N13: 5088 | O13: 4694 | P13: 5086 | Q13: 4972 | R13: 4516 | S13: 4718 | T13: 4527 | U13: 4795 | V13: 4194 | W13: 5114 | X13: 7209 | Y13: 4207 | Z13: 4298 | AA13: 4284 | AB13: 4446 | AC13: 3812 | AD13: 4927 | AE13: 4900
A14: 1.2 | B14: 3065 | C14: 2407 | D14: 2050 | E14: 4043 | F14: 4829 | G14: 4780 | H14: 4851 | I14: 7404 | J14: 4671 | K14: 4569 | L14: 5695 | M14: 4587 | N14: 5349 | O14: 4955 | P14: 5347 | Q14: 5233 | R14: 4778 | S14: 4979 | T14: 4788 | U14: 5054 | V14: 4455 | W14: 5376 | X14: 7470 | Y14: 4468 | Z14: 4558 | AA14: 4543 | AB14: 4707 | AC14: 4072 | AD14: 5188 | AE14: 5162
... A58: 20 | B58: 32016 | C58: 26501 | D58: 14313 | E58: 57332 | F58: 57593 | G58: 51661 | H58: 53021 | I58: 102382 | J58: 49148 | K58: 50023 | L58: 50604 | M58: 50712 | N58: 52228 | O58: 50351 | P58: 73567 | Q58: 52496 | R58: 49379 | S58: 51142 | T58: 51073 | U58: 49702 | V58: 48549 | W58: 50396 | X58: 86945 | Y58: 48489 | Z58: 57185 | AA58: 49603 | AB58: 59477 | AC58: 31725 | AD58: 50066 | AE58: 49879

Sheet 合計比較
A1: 同条件での合計送料の比較（円・eBay SpeedPAK Economy）。各列とも燃油12%・固定手数料込みの「支払い総額」ベース（通常時）
A2: ※EU繁忙期割増34円(11/1〜12/31)や豪州の検疫等の条件付き費用は含まない。アメリカ諸費用込みはアメリカタブの申告価格・関税率入力に連動（初期値$50・15%）
A3: 重量kg最大 | B3: アメリカ本土48州（燃油・通関245円込み） | C3: アメリカ諸費用込み（＋関税） | D3: イギリス（燃油込み） | E3: オーストラリア（燃油込み） | F3: EU:ドイツ（燃油・関税込み） | G3: EU:フランス（燃油・関税込み） | H3: EU最安（額・込み） | I3: EU最安（国） | J3: EU最高（額・込み） | K3: EU最高（国）
A4: =基礎データ!A3 | B4: =基礎データ!B3*(1+前提・出典!$B$2)+前提・出典!$B$5 | C4: =B4+アメリカ!$B$6 | D4: =基礎データ!C3*(1+前提・出典!$B$2) | E4: =基礎データ!D3*(1+前提・出典!$B$2) | F4: =基礎データ!E3*(1+前提・出典!$B$2)+前提・出典!$B$3*(1+前提・出典!$B$4) | G4: =基礎データ!O3*(1+前提・出典!$B$2)+前提・出典!$B$3*(1+前提・出典!$B$4) | H4: =MIN(基礎データ!$E3:$AE3)*(1+前提・出典!$B$2)+前提・出典!$B$3*(1+前提・出典!$B$4) | I4: =INDEX(基礎データ!$E$2:$AE$2,MATCH(MIN(基礎データ!$E3:$AE3),基礎データ!$E3:$AE3,0)) | J4: =MAX(基礎データ!$E3:$AE3)*(1+前提・出典!$B$2)+前提・出典!$B$3*(1+前提・出典!$B$4) | K4: =INDEX(基礎データ!$E$2:$AE$2,MATCH(MAX(基礎データ!$E3:$AE3),基礎データ!$E3:$AE3,0))
A5: =基礎データ!A4 | B5: =基礎データ!B4*(1+前提・出典!$B$2)+前提・出典!$B$5 | C5: =B5+アメリカ!$B$6 | D5: =基礎データ!C4*(1+前提・出典!$B$2) | E5: =基礎データ!D4*(1+前提・出典!$B$2) | F5: =基礎データ!E4*(1+前提・出典!$B$2)+前提・出典!$B$3*(1+前提・出典!$B$4) | G5: =基礎データ!O4*(1+前提・出典!$B$2)+前提・出典!$B$3*(1+前提・出典!$B$4) | H5: =MIN(基礎データ!$E4:$AE4)*(1+前提・出典!$B$2)+前提・出典!$B$3*(1+前提・出典!$B$4) | I5: =INDEX(基礎データ!$E$2:$AE$2,MATCH(MIN(基礎データ!$E4:$AE4),基礎データ!$E4:$AE4,0)) | J5: =MAX(基礎データ!$E4:$AE4)*(1+前提・出典!$B$2)+前提・出典!$B$3*(1+前提・出典!$B$4) | K5: =INDEX(基礎データ!$E$2:$AE$2,MATCH(MAX(基礎データ!$E4:$AE4),基礎データ!$E4:$AE4,0))
A6: =基礎データ!A5 | B6: =基礎データ!B5*(1+前提・出典!$B$2)+前提・出典!$B$5 | C6: =B6+アメリカ!$B$6 | D6: =基礎データ!C5*(1+前提・出典!$B$2) | E6: =基礎データ!D5*(1+前提・出典!$B$2) | F6: =基礎データ!E5*(1+前提・出典!$B$2)+前提・出典!$B$3*(1+前提・出典!$B$4) | G6: =基礎データ!O5*(1+前提・出典!$B$2)+前提・出典!$B$3*(1+前提・出典!$B$4) | H6: =MIN(基礎データ!$E5:$AE5)*(1+前提・出典!$B$2)+前提・出典!$B$3*(1+前提・出典!$B$4) | I6: =INDEX(基礎データ!$E$2:$AE$2,MATCH(MIN(基礎データ!$E5:$AE5),基礎データ!$E5:$AE5,0)) | J6: =MAX(基礎データ!$E5:$AE5)*(1+前提・出典!$B$2)+前提・出典!$B$3*(1+前提・出典!$B$4) | K6: =INDEX(基礎データ!$E$2:$AE$2,MATCH(MAX(基礎データ!$E5:$AE5),基礎データ!$E5:$AE5,0))
A7: =基礎データ!A6 | B7: =基礎データ!B6*(1+前提・出典!$B$2)+前提・出典!$B$5 | C7: =B7+アメリカ!$B$6 | D7: =基礎データ!C6*(1+前提・出典!$B$2) | E7: =基礎データ!D6*(1+前提・出典!$B$2) | F7: =基礎データ!E6*(1+前提・出典!$B$2)+前提・出典!$B$3*(1+前提・出典!$B$4) | G7: =基礎データ!O6*(1+前提・出典!$B$2)+前提・出典!$B$3*(1+前提・出典!$B$4) | H7: =MIN(基礎データ!$E6:$AE6)*(1+前提・出典!$B$2)+前提・出典!$B$3*(1+前提・出典!$B$4) | I7: =INDEX(基礎データ!$E$2:$AE$2,MATCH(MIN(基礎データ!$E6:$AE6),基礎データ!$E6:$AE6,0)) | J7: =MAX(基礎データ!$E6:$AE6)*(1+前提・出典!$B$2)+前提・出典!$B$3*(1+前提・出典!$B$4) | K7: =INDEX(基礎データ!$E$2:$AE$2,MATCH(MAX(基礎データ!$E6:$AE6),基礎データ!$E6:$AE6,0))
A8: =基礎データ!A7 | B8: =基礎データ!B7*(1+前提・出典!$B$2)+前提・出典!$B$5 | C8: =B8+アメリカ!$B$6 | D8: =基礎データ!C7*(1+前提・出典!$B$2) | E8: =基礎データ!D7*(1+前提・出典!$B$2) | F8: =基礎データ!E7*(1+前提・出典!$B$2)+前提・出典!$B$3*(1+前提・出典!$B$4) | G8: =基礎データ!O7*(1+前提・出典!$B$2)+前提・出典!$B$3*(1+前提・出典!$B$4) | H8: =MIN(基礎データ!$E7:$AE7)*(1+前提・出典!$B$2)+前提・出典!$B$3*(1+前提・出典!$B$4) | I8: =INDEX(基礎データ!$E$2:$AE$2,MATCH(MIN(基礎データ!$E7:$AE7),基礎データ!$E7:$AE7,0)) | J8: =MAX(基礎データ!$E7:$AE7)*(1+前提・出典!$B$2)+前提・出典!$B$3*(1+前提・出典!$B$4) | K8: =INDEX(基礎データ!$E$2:$AE$2,MATCH(MAX(基礎データ!$E7:$AE7),基礎データ!$E7:$AE7,0))
A9: =基礎データ!A8 | B9: =基礎データ!B8*(1+前提・出典!$B$2)+前提・出典!$B$5 | C9: =B9+アメリカ!$B$6 | D9: =基礎データ!C8*(1+前提・出典!$B$2) | E9: =基礎データ!D8*(1+前提・出典!$B$2) | F9: =基礎データ!E8*(1+前提・出典!$B$2)+前提・出典!$B$3*(1+前提・出典!$B$4) | G9: =基礎データ!O8*(1+前提・出典!$B$2)+前提・出典!$B$3*(1+前提・出典!$B$4) | H9: =MIN(基礎データ!$E8:$AE8)*(1+前提・出典!$B$2)+前提・出典!$B$3*(1+前提・出典!$B$4) | I9: =INDEX(基礎データ!$E$2:$AE$2,MATCH(MIN(基礎データ!$E8:$AE8),基礎データ!$E8:$AE8,0)) | J9: =MAX(基礎データ!$E8:$AE8)*(1+前提・出典!$B$2)+前提・出典!$B$3*(1+前提・出典!$B$4) | K9: =INDEX(基礎データ!$E$2:$AE$2,MATCH(MAX(基礎データ!$E8:$AE8),基礎データ!$E8:$AE8,0))
A10: =基礎データ!A9 | B10: =基礎データ!B9*(1+前提・出典!$B$2)+前提・出典!$B$5 | C10: =B10+アメリカ!$B$6 | D10: =基礎データ!C9*(1+前提・出典!$B$2) | E10: =基礎データ!D9*(1+前提・出典!$B$2) | F10: =基礎データ!E9*(1+前提・出典!$B$2)+前提・出典!$B$3*(1+前提・出典!$B$4) | G10: =基礎データ!O9*(1+前提・出典!$B$2)+前提・出典!$B$3*(1+前提・出典!$B$4) | H10: =MIN(基礎データ!$E9:$AE9)*(1+前提・出典!$B$2)+前提・出典!$B$3*(1+前提・出典!$B$4) | I10: =INDEX(基礎データ!$E$2:$AE$2,MATCH(MIN(基礎データ!$E9:$AE9),基礎データ!$E9:$AE9,0)) | J10: =MAX(基礎データ!$E9:$AE9)*(1+前提・出典!$B$2)+前提・出典!$B$3*(1+前提・出典!$B$4) | K10: =INDEX(基礎データ!$E$2:$AE$2,MATCH(MAX(基礎データ!$E9:$AE9),基礎データ!$E9:$AE9,0))
A11: =基礎データ!A10 | B11: =基礎データ!B10*(1+前提・出典!$B$2)+前提・出典!$B$5 | C11: =B11+アメリカ!$B$6 | D11: =基礎データ!C10*(1+前提・出典!$B$2) | E11: =基礎データ!D10*(1+前提・出典!$B$2) | F11: =基礎データ!E10*(1+前提・出典!$B$2)+前提・出典!$B$3*(1+前提・出典!$B$4) | G11: =基礎データ!O10*(1+前提・出典!$B$2)+前提・出典!$B$3*(1+前提・出典!$B$4) | H11: =MIN(基礎データ!$E10:$AE10)*(1+前提・出典!$B$2)+前提・出典!$B$3*(1+前提・出典!$B$4) | I11: =INDEX(基礎データ!$E$2:$AE$2,MATCH(MIN(基礎データ!$E10:$AE10),基礎データ!$E10:$AE10,0)) | J11: =MAX(基礎データ!$E10:$AE10)*(1+前提・出典!$B$2)+前提・出典!$B$3*(1+前提・出典!$B$4) | K11: =INDEX(基礎データ!$E$2:$AE$2,MATCH(MAX(基礎データ!$E10:$AE10),基礎データ!$E10:$AE10,0))
A12: =基礎データ!A11 | B12: =基礎データ!B11*(1+前提・出典!$B$2)+前提・出典!$B$5 | C12: =B12+アメリカ!$B$6 | D12: =基礎データ!C11*(1+前提・出典!$B$2) | E12: =基礎データ!D11*(1+前提・出典!$B$2) | F12: =基礎データ!E11*(1+前提・出典!$B$2)+前提・出典!$B$3*(1+前提・出典!$B$4) | G12: =基礎データ!O11*(1+前提・出典!$B$2)+前提・出典!$B$3*(1+前提・出典!$B$4) | H12: =MIN(基礎データ!$E11:$AE11)*(1+前提・出典!$B$2)+前提・出典!$B$3*(1+前提・出典!$B$4) | I12: =INDEX(基礎データ!$E$2:$AE$2,MATCH(MIN(基礎データ!$E11:$AE11),基礎データ!$E11:$AE11,0)) | J12: =MAX(基礎データ!$E11:$AE11)*(1+前提・出典!$B$2)+前提・出典!$B$3*(1+前提・出典!$B$4) | K12: =INDEX(基礎データ!$E$2:$AE$2,MATCH(MAX(基礎データ!$E11:$AE11),基礎データ!$E11:$AE11,0))
A13: =基礎データ!A12 | B13: =基礎データ!B12*(1+前提・出典!$B$2)+前提・出典!$B$5 | C13: =B13+アメリカ!$B$6 | D13: =基礎データ!C12*(1+前提・出典!$B$2) | E13: =基礎データ!D12*(1+前提・出典!$B$2) | F13: =基礎データ!E12*(1+前提・出典!$B$2)+前提・出典!$B$3*(1+前提・出典!$B$4) | G13: =基礎データ!O12*(1+前提・出典!$B$2)+前提・出典!$B$3*(1+前提・出典!$B$4) | H13: =MIN(基礎データ!$E12:$AE12)*(1+前提・出典!$B$2)+前提・出典!$B$3*(1+前提・出典!$B$4) | I13: =INDEX(基礎データ!$E$2:$AE$2,MATCH(MIN(基礎データ!$E12:$AE12),基礎データ!$E12:$AE12,0)) | J13: =MAX(基礎データ!$E12:$AE12)*(1+前提・出典!$B$2)+前提・出典!$B$3*(1+前提・出典!$B$4) | K13: =INDEX(基礎データ!$E$2:$AE$2,MATCH(MAX(基礎データ!$E12:$AE12),基礎データ!$E12:$AE12,0))
A14: =基礎データ!A13 | B14: =基礎データ!B13*(1+前提・出典!$B$2)+前提・出典!$B$5 | C14: =B14+アメリカ!$B$6 | D14: =基礎データ!C13*(1+前提・出典!$B$2) | E14: =基礎データ!D13*(1+前提・出典!$B$2) | F14: =基礎データ!E13*(1+前提・出典!$B$2)+前提・出典!$B$3*(1+前提・出典!$B$4) | G14: =基礎データ!O13*(1+前提・出典!$B$2)+前提・出典!$B$3*(1+前提・出典!$B$4) | H14: =MIN(基礎データ!$E13:$AE13)*(1+前提・出典!$B$2)+前提・出典!$B$3*(1+前提・出典!$B$4) | I14: =INDEX(基礎データ!$E$2:$AE$2,MATCH(MIN(基礎データ!$E13:$AE13),基礎データ!$E13:$AE13,0)) | J14: =MAX(基礎データ!$E13:$AE13)*(1+前提・出典!$B$2)+前提・出典!$B$3*(1+前提・出典!$B$4) | K14: =INDEX(基礎データ!$E$2:$AE$2,MATCH(MAX(基礎データ!$E13:$AE13),基礎データ!$E13:$AE13,0))
A15: =基礎データ!A14 | B15: =基礎データ!B14*(1+前提・出典!$B$2)+前提・出典!$B$5 | C15: =B15+アメリカ!$B$6 | D15: =基礎データ!C14*(1+前提・出典!$B$2) | E15: =基礎データ!D14*(1+前提・出典!$B$2) | F15: =基礎データ!E14*(1+前提・出典!$B$2)+前提・出典!$B$3*(1+前提・出典!$B$4) | G15: =基礎データ!O14*(1+前提・出典!$B$2)+前提・出典!$B$3*(1+前提・出典!$B$4) | H15: =MIN(基礎データ!$E14:$AE14)*(1+前提・出典!$B$2)+前提・出典!$B$3*(1+前提・出典!$B$4) | I15: =INDEX(基礎データ!$E$2:$AE$2,MATCH(MIN(基礎データ!$E14:$AE14),基礎データ!$E14:$AE14,0)) | J15: =MAX(基礎データ!$E14:$AE14)*(1+前提・出典!$B$2)+前提・出典!$B$3*(1+前提・出典!$B$4) | K15: =INDEX(基礎データ!$E$2:$AE$2,MATCH(MAX(基礎データ!$E14:$AE14),基礎データ!$E14:$AE14,0))
... A59: =基礎データ!A58 | B59: =基礎データ!B58*(1+前提・出典!$B$2)+前提・出典!$B$5 | C59: =B59+アメリカ!$B$6 | D59: =基礎データ!C58*(1+前提・出典!$B$2) | E59: =基礎データ!D58*(1+前提・出典!$B$2) | F59: =基礎データ!E58*(1+前提・出典!$B$2)+前提・出典!$B$3*(1+前提・出典!$B$4) | G59: =基礎データ!O58*(1+前提・出典!$B$2)+前提・出典!$B$3*(1+前提・出典!$B$4) | H59: =MIN(基礎データ!$E58:$AE58)*(1+前提・出典!$B$2)+前提・出典!$B$3*(1+前提・出典!$B$4) | I59: =INDEX(基礎データ!$E$2:$AE$2,MATCH(MIN(基礎データ!$E58:$AE58),基礎データ!$E58:$AE58,0)) | J59: =MAX(基礎データ!$E58:$AE58)*(1+前提・出典!$B$2)+前提・出典!$B$3*(1+前提・出典!$B$4) | K59: =INDEX(基礎データ!$E$2:$AE$2,MATCH(MAX(基礎データ!$E58:$AE58),基礎データ!$E58:$AE58,0))

Sheet EU27国別合計
A1: EU27カ国別の合計送料（円・サーチャージ込み）＝基本送料×(1+燃油12%)＋関税555円×(1+処理2.1%)
A2: 重量kg最大 | B2: DE ドイツ | C2: AT オーストリア | D2: BE ベルギー | E2: BG ブルガリア | F2: CY キプロス | G2: CZ チェコ | H2: DK デンマーク | I2: EE エストニア | J2: ES スペイン | K2: FI フィンランド | L2: FR フランス | M2: GR ギリシャ | N2: HR クロアチア | O2: HU ハンガリー | P2: IE アイルランド | Q2: IT イタリア | R2: LT リトアニア | S2: LU ルクセンブルク | T2: LV ラトビア | U2: MT マルタ | V2: NL オランダ | W2: PL ポーランド | X2: PT ポルトガル | Y2: RO ルーマニア | Z2: SE スウェーデン | AA2: SI スロベニア | AB2: SK スロバキア
A3: =基礎データ!A3 | B3: =基礎データ!E3*(1+前提・出典!$B$2)+前提・出典!$B$3*(1+前提・出典!$B$4) | C3: =基礎データ!F3*(1+前提・出典!$B$2)+前提・出典!$B$3*(1+前提・出典!$B$4) | D3: =基礎データ!G3*(1+前提・出典!$B$2)+前提・出典!$B$3*(1+前提・出典!$B$4) | E3: =基礎データ!H3*(1+前提・出典!$B$2)+前提・出典!$B$3*(1+前提・出典!$B$4) | F3: =基礎データ!I3*(1+前提・出典!$B$2)+前提・出典!$B$3*(1+前提・出典!$B$4) | G3: =基礎データ!J3*(1+前提・出典!$B$2)+前提・出典!$B$3*(1+前提・出典!$B$4) | H3: =基礎データ!K3*(1+前提・出典!$B$2)+前提・出典!$B$3*(1+前提・出典!$B$4) | I3: =基礎データ!L3*(1+前提・出典!$B$2)+前提・出典!$B$3*(1+前提・出典!$B$4) | ... AB3: =基礎データ!AE3*(1+前提・出典!$B$2)+前提・出典!$B$3*(1+前提・出典!$B$4)
A4: =基礎データ!A4 | B4: =基礎データ!E4*(1+前提・出典!$B$2)+前提・出典!$B$3*(1+前提・出典!$B$4) | C4: =基礎データ!F4*(1+前提・出典!$B$2)+前提・出典!$B$3*(1+前提・出典!$B$4) | D4: =基礎データ!G4*(1+前提・出典!$B$2)+前提・出典!$B$3*(1+前提・出典!$B$4) | E4: =基礎データ!H4*(1+前提・出典!$B$2)+前提・出典!$B$3*(1+前提・出典!$B$4) | F4: =基礎データ!I4*(1+前提・出典!$B$2)+前提・出典!$B$3*(1+前提・出典!$B$4) | G4: =基礎データ!J4*(1+前提・出典!$B$2)+前提・出典!$B$3*(1+前提・出典!$B$4) | H4: =基礎データ!K4*(1+前提・出典!$B$2)+前提・出典!$B$3*(1+前提・出典!$B$4) | I4: =基礎データ!L4*(1+前提・出典!$B$2)+前提・出典!$B$3*(1+前提・出典!$B$4) | ... AB4: =基礎データ!AE4*(1+前提・出典!$B$2)+前提・出典!$B$3*(1+前提・出典!$B$4)
A5: =基礎データ!A5 | B5: =基礎データ!E5*(1+前提・出典!$B$2)+前提・出典!$B$3*(1+前提・出典!$B$4) | C5: =基礎データ!F5*(1+前提・出典!$B$2)+前提・出典!$B$3*(1+前提・出典!$B$4) | D5: =基礎データ!G5*(1+前提・出典!$B$2)+前提・出典!$B$3*(1+前提・出典!$B$4) | E5: =基礎データ!H5*(1+前提・出典!$B$2)+前提・出典!$B$3*(1+前提・出典!$B$4) | F5: =基礎データ!I5*(1+前提・出典!$B$2)+前提・出典!$B$3*(1+前提・出典!$B$4) | G5: =基礎データ!J5*(1+前提・出典!$B$2)+前提・出典!$B$3*(1+前提・出典!$B$4) | H5: =基礎データ!K5*(1+前提・出典!$B$2)+前提・出典!$B$3*(1+前提・出典!$B$4) | I5: =基礎データ!L5*(1+前提・出典!$B$2)+前提・出典!$B$3*(1+前提・出典!$B$4) | ... AB5: =基礎データ!AE5*(1+前提・出典!$B$2)+前提・出典!$B$3*(1+前提・出典!$B$4)
A6: =基礎データ!A6 | B6: =基礎データ!E6*(1+前提・出典!$B$2)+前提・出典!$B$3*(1+前提・出典!$B$4) | C6: =基礎データ!F6*(1+前提・出典!$B$2)+前提・出典!$B$3*(1+前提・出典!$B$4) | D6: =基礎データ!G6*(1+前提・出典!$B$2)+前提・出典!$B$3*(1+前提・出典!$B$4) | E6: =基礎データ!H6*(1+前提・出典!$B$2)+前提・出典!$B$3*(1+前提・出典!$B$4) | F6: =基礎データ!I6*(1+前提・出典!$B$2)+前提・出典!$B$3*(1+前提・出典!$B$4) | G6: =基礎データ!J6*(1+前提・出典!$B$2)+前提・出典!$B$3*(1+前提・出典!$B$4) | H6: =基礎データ!K6*(1+前提・出典!$B$2)+前提・出典!$B$3*(1+前提・出典!$B$4) | I6: =基礎データ!L6*(1+前提・出典!$B$2)+前提・出典!$B$3*(1+前提・出典!$B$4) | ... AB6: =基礎データ!AE6*(1+前提・出典!$B$2)+前提・出典!$B$3*(1+前提・出典!$B$4)
A7: =基礎データ!A7 | B7: =基礎データ!E7*(1+前提・出典!$B$2)+前提・出典!$B$3*(1+前提・出典!$B$4) | C7: =基礎データ!F7*(1+前提・出典!$B$2)+前提・出典!$B$3*(1+前提・出典!$B$4) | D7: =基礎データ!G7*(1+前提・出典!$B$2)+前提・出典!$B$3*(1+前提・出典!$B$4) | E7: =基礎データ!H7*(1+前提・出典!$B$2)+前提・出典!$B$3*(1+前提・出典!$B$4) | F7: =基礎データ!I7*(1+前提・出典!$B$2)+前提・出典!$B$3*(1+前提・出典!$B$4) | G7: =基礎データ!J7*(1+前提・出典!$B$2)+前提・出典!$B$3*(1+前提・出典!$B$4) | H7: =基礎データ!K7*(1+前提・出典!$B$2)+前提・出典!$B$3*(1+前提・出典!$B$4) | I7: =基礎データ!L7*(1+前提・出典!$B$2)+前提・出典!$B$3*(1+前提・出典!$B$4) | ... AB7: =基礎データ!AE7*(1+前提・出典!$B$2)+前提・出典!$B$3*(1+前提・出典!$B$4)
A8: =基礎データ!A8 | B8: =基礎データ!E8*(1+前提・出典!$B$2)+前提・出典!$B$3*(1+前提・出典!$B$4) | C8: =基礎データ!F8*(1+前提・出典!$B$2)+前提・出典!$B$3*(1+前提・出典!$B$4) | D8: =基礎データ!G8*(1+前提・出典!$B$2)+前提・出典!$B$3*(1+前提・出典!$B$4) | E8: =基礎データ!H8*(1+前提・出典!$B$2)+前提・出典!$B$3*(1+前提・出典!$B$4) | F8: =基礎データ!I8*(1+前提・出典!$B$2)+前提・出典!$B$3*(1+前提・出典!$B$4) | G8: =基礎データ!J8*(1+前提・出典!$B$2)+前提・出典!$B$3*(1+前提・出典!$B$4) | H8: =基礎データ!K8*(1+前提・出典!$B$2)+前提・出典!$B$3*(1+前提・出典!$B$4) | I8: =基礎データ!L8*(1+前提・出典!$B$2)+前提・出典!$B$3*(1+前提・出典!$B$4) | ... AB8: =基礎データ!AE8*(1+前提・出典!$B$2)+前提・出典!$B$3*(1+前提・出典!$B$4)
A9: =基礎データ!A9 | B9: =基礎データ!E9*(1+前提・出典!$B$2)+前提・出典!$B$3*(1+前提・出典!$B$4) | C9: =基礎データ!F9*(1+前提・出典!$B$2)+前提・出典!$B$3*(1+前提・出典!$B$4) | D9: =基礎データ!G9*(1+前提・出典!$B$2)+前提・出典!$B$3*(1+前提・出典!$B$4) | E9: =基礎データ!H9*(1+前提・出典!$B$2)+前提・出典!$B$3*(1+前提・出典!$B$4) | F9: =基礎データ!I9*(1+前提・出典!$B$2)+前提・出典!$B$3*(1+前提・出典!$B$4) | G9: =基礎データ!J9*(1+前提・出典!$B$2)+前提・出典!$B$3*(1+前提・出典!$B$4) | H9: =基礎データ!K9*(1+前提・出典!$B$2)+前提・出典!$B$3*(1+前提・出典!$B$4) | I9: =基礎データ!L9*(1+前提・出典!$B$2)+前提・出典!$B$3*(1+前提・出典!$B$4) | ... AB9: =基礎データ!AE9*(1+前提・出典!$B$2)+前提・出典!$B$3*(1+前提・出典!$B$4)
A10: =基礎データ!A10 | B10: =基礎データ!E10*(1+前提・出典!$B$2)+前提・出典!$B$3*(1+前提・出典!$B$4) | C10: =基礎データ!F10*(1+前提・出典!$B$2)+前提・出典!$B$3*(1+前提・出典!$B$4) | D10: =基礎データ!G10*(1+前提・出典!$B$2)+前提・出典!$B$3*(1+前提・出典!$B$4) | E10: =基礎データ!H10*(1+前提・出典!$B$2)+前提・出典!$B$3*(1+前提・出典!$B$4) | F10: =基礎データ!I10*(1+前提・出典!$B$2)+前提・出典!$B$3*(1+前提・出典!$B$4) | G10: =基礎データ!J10*(1+前提・出典!$B$2)+前提・出典!$B$3*(1+前提・出典!$B$4) | H10: =基礎データ!K10*(1+前提・出典!$B$2)+前提・出典!$B$3*(1+前提・出典!$B$4) | I10: =基礎データ!L10*(1+前提・出典!$B$2)+前提・出典!$B$3*(1+前提・出典!$B$4) | ... AB10: =基礎データ!AE10*(1+前提・出典!$B$2)+前提・出典!$B$3*(1+前提・出典!$B$4)
A11: =基礎データ!A11 | B11: =基礎データ!E11*(1+前提・出典!$B$2)+前提・出典!$B$3*(1+前提・出典!$B$4) | C11: =基礎データ!F11*(1+前提・出典!$B$2)+前提・出典!$B$3*(1+前提・出典!$B$4) | D11: =基礎データ!G11*(1+前提・出典!$B$2)+前提・出典!$B$3*(1+前提・出典!$B$4) | E11: =基礎データ!H11*(1+前提・出典!$B$2)+前提・出典!$B$3*(1+前提・出典!$B$4) | F11: =基礎データ!I11*(1+前提・出典!$B$2)+前提・出典!$B$3*(1+前提・出典!$B$4) | G11: =基礎データ!J11*(1+前提・出典!$B$2)+前提・出典!$B$3*(1+前提・出典!$B$4) | H11: =基礎データ!K11*(1+前提・出典!$B$2)+前提・出典!$B$3*(1+前提・出典!$B$4) | I11: =基礎データ!L11*(1+前提・出典!$B$2)+前提・出典!$B$3*(1+前提・出典!$B$4) | ... AB11: =基礎データ!AE11*(1+前提・出典!$B$2)+前提・出典!$B$3*(1+前提・出典!$B$4)
A12: =基礎データ!A12 | B12: =基礎データ!E12*(1+前提・出典!$B$2)+前提・出典!$B$3*(1+前提・出典!$B$4) | C12: =基礎データ!F12*(1+前提・出典!$B$2)+前提・出典!$B$3*(1+前提・出典!$B$4) | D12: =基礎データ!G12*(1+前提・出典!$B$2)+前提・出典!$B$3*(1+前提・出典!$B$4) | E12: =基礎データ!H12*(1+前提・出典!$B$2)+前提・出典!$B$3*(1+前提・出典!$B$4) | F12: =基礎データ!I12*(1+前提・出典!$B$2)+前提・出典!$B$3*(1+前提・出典!$B$4) | G12: =基礎データ!J12*(1+前提・出典!$B$2)+前提・出典!$B$3*(1+前提・出典!$B$4) | H12: =基礎データ!K12*(1+前提・出典!$B$2)+前提・出典!$B$3*(1+前提・出典!$B$4) | I12: =基礎データ!L12*(1+前提・出典!$B$2)+前提・出典!$B$3*(1+前提・出典!$B$4) | ... AB12: =基礎データ!AE12*(1+前提・出典!$B$2)+前提・出典!$B$3*(1+前提・出典!$B$4)
A13: =基礎データ!A13 | B13: =基礎データ!E13*(1+前提・出典!$B$2)+前提・出典!$B$3*(1+前提・出典!$B$4) | C13: =基礎データ!F13*(1+前提・出典!$B$2)+前提・出典!$B$3*(1+前提・出典!$B$4) | D13: =基礎データ!G13*(1+前提・出典!$B$2)+前提・出典!$B$3*(1+前提・出典!$B$4) | E13: =基礎データ!H13*(1+前提・出典!$B$2)+前提・出典!$B$3*(1+前提・出典!$B$4) | F13: =基礎データ!I13*(1+前提・出典!$B$2)+前提・出典!$B$3*(1+前提・出典!$B$4) | G13: =基礎データ!J13*(1+前提・出典!$B$2)+前提・出典!$B$3*(1+前提・出典!$B$4) | H13: =基礎データ!K13*(1+前提・出典!$B$2)+前提・出典!$B$3*(1+前提・出典!$B$4) | I13: =基礎データ!L13*(1+前提・出典!$B$2)+前提・出典!$B$3*(1+前提・出典!$B$4) | ... AB13: =基礎データ!AE13*(1+前提・出典!$B$2)+前提・出典!$B$3*(1+前提・出典!$B$4)
A14: =基礎データ!A14 | B14: =基礎データ!E14*(1+前提・出典!$B$2)+前提・出典!$B$3*(1+前提・出典!$B$4) | C14: =基礎データ!F14*(1+前提・出典!$B$2)+前提・出典!$B$3*(1+前提・出典!$B$4) | D14: =基礎データ!G14*(1+前提・出典!$B$2)+前提・出典!$B$3*(1+前提・出典!$B$4) | E14: =基礎データ!H14*(1+前提・出典!$B$2)+前提・出典!$B$3*(1+前提・出典!$B$4) | F14: =基礎データ!I14*(1+前提・出典!$B$2)+前提・出典!$B$3*(1+前提・出典!$B$4) | G14: =基礎データ!J14*(1+前提・出典!$B$2)+前提・出典!$B$3*(1+前提・出典!$B$4) | H14: =基礎データ!K14*(1+前提・出典!$B$2)+前提・出典!$B$3*(1+前提・出典!$B$4) | I14: =基礎データ!L14*(1+前提・出典!$B$2)+前提・出典!$B$3*(1+前提・出典!$B$4) | ... AB14: =基礎データ!AE14*(1+前提・出典!$B$2)+前提・出典!$B$3*(1+前提・出典!$B$4)
... A58: =基礎データ!A58 | B58: =基礎データ!E58*(1+前提・出典!$B$2)+前提・出典!$B$3*(1+前提・出典!$B$4) | C58: =基礎データ!F58*(1+前提・出典!$B$2)+前提・出典!$B$3*(1+前提・出典!$B$4) | D58: =基礎データ!G58*(1+前提・出典!$B$2)+前提・出典!$B$3*(1+前提・出典!$B$4) | E58: =基礎データ!H58*(1+前提・出典!$B$2)+前提・出典!$B$3*(1+前提・出典!$B$4) | F58: =基礎データ!I58*(1+前提・出典!$B$2)+前提・出典!$B$3*(1+前提・出典!$B$4) | G58: =基礎データ!J58*(1+前提・出典!$B$2)+前提・出典!$B$3*(1+前提・出典!$B$4) | H58: =基礎データ!K58*(1+前提・出典!$B$2)+前提・出典!$B$3*(1+前提・出典!$B$4) | I58: =基礎データ!L58*(1+前提・出典!$B$2)+前提・出典!$B$3*(1+前提・出典!$B$4) | ... AB58: =基礎データ!AE58*(1+前提・出典!$B$2)+前提・出典!$B$3*(1+前提・出典!$B$4)

Sheet アメリカ
A1: アメリカ向け料金表（円・SpeedPAK Economy）。合計＝基本送料×(1+燃油)＋輸入通関手数料245円。関税込み合計＝合計＋関税上乗せ額。出典: 料金ガイドp.6-7
A3: 申告価格（USD） | B3: 50 | C3: 商品価格のみ（送料・保険を除く）。青字＝変更可
A4: 想定関税率 | B4: 0.15 | C4: 従来運用の想定値。実際の事前設定レートは料金ガイド非公表・随時変更のため要確認
A5: 為替（円/ドル） | B5: =前提・出典!$B$6 | C5: 前提・出典タブから参照
A6: 関税上乗せ額（円） | B6: =B3*B5*B4*(1+前提・出典!$B$4) | C6: ＝申告価格×為替×関税率×(1+処理手数料2.1%)
A8: 重量kg最大 | B8: 本土48州 基本送料 | C8: 本土48州 合計（関税除く） | D8: 本土48州 関税込み合計 | E8: 48州以外 基本送料 | F8: 48州以外 合計（関税除く） | G8: 48州以外 関税込み合計
A9: 0.1 | B9: 1157 | C9: =B9*(1+前提・出典!$B$2)+前提・出典!$B$5 | D9: =C9+$B$6 | E9: 1226 | F9: =E9*(1+前提・出典!$B$2)+前提・出典!$B$5 | G9: =F9+$B$6
A10: 0.2 | B10: 1289 | C10: =B10*(1+前提・出典!$B$2)+前提・出典!$B$5 | D10: =C10+$B$6 | E10: 1393 | F10: =E10*(1+前提・出典!$B$2)+前提・出典!$B$5 | G10: =F10+$B$6
A11: 0.3 | B11: 1491 | C11: =B11*(1+前提・出典!$B$2)+前提・出典!$B$5 | D11: =C11+$B$6 | E11: 1703 | F11: =E11*(1+前提・出典!$B$2)+前提・出典!$B$5 | G11: =F11+$B$6
A12: 0.4 | B12: 1677 | C12: =B12*(1+前提・出典!$B$2)+前提・出典!$B$5 | D12: =C12+$B$6 | E12: 2005 | F12: =E12*(1+前提・出典!$B$2)+前提・出典!$B$5 | G12: =F12+$B$6
A13: 0.5 | B13: 1943 | C13: =B13*(1+前提・出典!$B$2)+前提・出典!$B$5 | D13: =C13+$B$6 | E13: 2473 | F13: =E13*(1+前提・出典!$B$2)+前提・出典!$B$5 | G13: =F13+$B$6
A14: 0.6 | B14: 2096 | C14: =B14*(1+前提・出典!$B$2)+前提・出典!$B$5 | D14: =C14+$B$6 | E14: 2640 | F14: =E14*(1+前提・出典!$B$2)+前提・出典!$B$5 | G14: =F14+$B$6
A15: 0.7 | B15: 2189 | C15: =B15*(1+前提・出典!$B$2)+前提・出典!$B$5 | D15: =C15+$B$6 | E15: 2733 | F15: =E15*(1+前提・出典!$B$2)+前提・出典!$B$5 | G15: =F15+$B$6
A16: 0.8 | B16: 2549 | C16: =B16*(1+前提・出典!$B$2)+前提・出典!$B$5 | D16: =C16+$B$6 | E16: 3154 | F16: =E16*(1+前提・出典!$B$2)+前提・出典!$B$5 | G16: =F16+$B$6
A17: 0.9 | B17: 2660 | C17: =B17*(1+前提・出典!$B$2)+前提・出典!$B$5 | D17: =C17+$B$6 | E17: 3267 | F17: =E17*(1+前提・出典!$B$2)+前提・出典!$B$5 | G17: =F17+$B$6
A18: 1 | B18: 2848 | C18: =B18*(1+前提・出典!$B$2)+前提・出典!$B$5 | D18: =C18+$B$6 | E18: 3844 | F18: =E18*(1+前提・出典!$B$2)+前提・出典!$B$5 | G18: =F18+$B$6
A19: 1.1 | B19: 2958 | C19: =B19*(1+前提・出典!$B$2)+前提・出典!$B$5 | D19: =C19+$B$6 | E19: 3954 | F19: =E19*(1+前提・出典!$B$2)+前提・出典!$B$5 | G19: =F19+$B$6
A20: 1.2 | B20: 3065 | C20: =B20*(1+前提・出典!$B$2)+前提・出典!$B$5 | D20: =C20+$B$6 | E20: 4061 | F20: =E20*(1+前提・出典!$B$2)+前提・出典!$B$5 | G20: =F20+$B$6
... A54: 15 | B54: 24509 | C54: =B54*(1+前提・出典!$B$2)+前提・出典!$B$5 | D54: =C54+$B$6 | E54: 26555 | F54: =E54*(1+前提・出典!$B$2)+前提・出典!$B$5 | G54: =F54+$B$6
A55: 15.5 | B55: 25139 | C55: =B55*(1+前提・出典!$B$2)+前提・出典!$B$5 | D55: =C55+$B$6 | E55: - | F55: - | G55: -
A56: 16 | B56: 26547 | C56: =B56*(1+前提・出典!$B$2)+前提・出典!$B$5 | D56: =C56+$B$6 | E56: - | F56: - | G56: -
A57: 16.5 | B57: 27138 | C57: =B57*(1+前提・出典!$B$2)+前提・出典!$B$5 | D57: =C57+$B$6 | E57: - | F57: - | G57: -
A58: 17 | B58: 27817 | C58: =B58*(1+前提・出典!$B$2)+前提・出典!$B$5 | D58: =C58+$B$6 | E58: - | F58: - | G58: -
A59: 17.5 | B59: 28478 | C59: =B59*(1+前提・出典!$B$2)+前提・出典!$B$5 | D59: =C59+$B$6 | E59: - | F59: - | G59: -
A60: 18 | B60: 29144 | C60: =B60*(1+前提・出典!$B$2)+前提・出典!$B$5 | D60: =C60+$B$6 | E60: - | F60: - | G60: -
A61: 18.5 | B61: 29687 | C61: =B61*(1+前提・出典!$B$2)+前提・出典!$B$5 | D61: =C61+$B$6 | E61: - | F61: - | G61: -
A62: 19 | B62: 30372 | C62: =B62*(1+前提・出典!$B$2)+前提・出典!$B$5 | D62: =C62+$B$6 | E62: - | F62: - | G62: -
A63: 19.5 | B63: 31062 | C63: =B63*(1+前提・出典!$B$2)+前提・出典!$B$5 | D63: =C63+$B$6 | E63: - | F63: - | G63: -
A64: 20 | B64: 32016 | C64: =B64*(1+前提・出典!$B$2)+前提・出典!$B$5 | D64: =C64+$B$6 | E64: - | F64: - | G64: -
A65: 20.5 | B65: 32683 | C65: =B65*(1+前提・出典!$B$2)+前提・出典!$B$5 | D65: =C65+$B$6 | E65: - | F65: - | G65: -
A66: 21 | B66: 33410 | C66: =B66*(1+前提・出典!$B$2)+前提・出典!$B$5 | D66: =C66+$B$6 | E66: - | F66: - | G66: -
... A74: 25 | B74: 38625 | C74: =B74*(1+前提・出典!$B$2)+前提・出典!$B$5 | D74: =C74+$B$6 | E74: - | F74: - | G74: -

Sheet イギリス
A1: イギリス向け料金表（円・SpeedPAK Economy）。合計＝基本送料×(1+燃油12%)。他の固定手数料なし。£135以下のVATはeBayがバイヤーから徴収。出典: 料金ガイドp.10
A2: 重量kg最大 | B2: 基本送料 | C2: 合計（燃油込み）
A3: 0.1 | B3: 885 | C3: =B3*(1+前提・出典!$B$2)
A4: 0.2 | B4: 1012 | C4: =B4*(1+前提・出典!$B$2)
A5: 0.3 | B5: 1173 | C5: =B5*(1+前提・出典!$B$2)
A6: 0.4 | B6: 1349 | C6: =B6*(1+前提・出典!$B$2)
A7: 0.5 | B7: 1482 | C7: =B7*(1+前提・出典!$B$2)
A8: 0.6 | B8: 1606 | C8: =B8*(1+前提・出典!$B$2)
A9: 0.7 | B9: 1746 | C9: =B9*(1+前提・出典!$B$2)
A10: 0.8 | B10: 1856 | C10: =B10*(1+前提・出典!$B$2)
A11: 0.9 | B11: 2000 | C11: =B11*(1+前提・出典!$B$2)
A12: 1 | B12: 2113 | C12: =B12*(1+前提・出典!$B$2)
A13: 1.1 | B13: 2274 | C13: =B13*(1+前提・出典!$B$2)
A14: 1.2 | B14: 2407 | C14: =B14*(1+前提・出典!$B$2)
... A68: 25 | B68: 35282 | C68: =B68*(1+前提・出典!$B$2)

Sheet オーストラリア
A1: オーストラリア向け料金表（円・SpeedPAK Economy）。合計＝基本送料×(1+燃油12%)。通常時の固定手数料なし（検疫等はAUD1,000超や検査時のみ）。AUD1,000以下のGSTはeBayが徴収。出典: 料金ガイドp.17
A2: 重量kg最大 | B2: 基本送料 | C2: 合計（燃油込み）
A3: 0.1 | B3: 1077 | C3: =B3*(1+前提・出典!$B$2)
A4: 0.2 | B4: 1247 | C4: =B4*(1+前提・出典!$B$2)
A5: 0.3 | B5: 1422 | C5: =B5*(1+前提・出典!$B$2)
A6: 0.4 | B6: 1451 | C6: =B6*(1+前提・出典!$B$2)
A7: 0.5 | B7: 1537 | C7: =B7*(1+前提・出典!$B$2)
A8: 0.6 | B8: 1709 | C8: =B8*(1+前提・出典!$B$2)
A9: 0.7 | B9: 1742 | C9: =B9*(1+前提・出典!$B$2)
A10: 0.8 | B10: 1883 | C10: =B10*(1+前提・出典!$B$2)
A11: 0.9 | B11: 1950 | C11: =B11*(1+前提・出典!$B$2)
A12: 1 | B12: 1950 | C12: =B12*(1+前提・出典!$B$2)
A13: 1.1 | B13: 2017 | C13: =B13*(1+前提・出典!$B$2)
A14: 1.2 | B14: 2050 | C14: =B14*(1+前提・出典!$B$2)
... A63: 22.5 | B63: 14871 | C63: =B63*(1+前提・出典!$B$2)

Sheet サーチャージ構造
A1: 項目 | B1: アメリカ | C1: イギリス | D1: オーストラリア | E1: EU27
A2: 燃油サーチャージ | B2: 別途（8/1から12%） | C2: 別途（8/1から12%） | D2: 別途（8/1から12%） | E2: 別途（8/1から12%）
A3: 通関系の固定費 | B3: 輸入通関手数料 245円/件 | C3: なし | D3: なし（通常時） | E3: 関税555円/関税分類番号
A4: 関税の事前徴収 | B4: あり：申告額×事前設定レート＋関税額の2.1% | C4: なし（£135以下はeBayがVAT徴収） | D4: なし（AUD1,000以下はeBayがGST徴収） | E4: あり：555円/分類＋合計の2.1%
A5: 条件付き費用 | B5: 規定外寸法 2,475円 | C5: 異常時のみ（申告取消1,000円等） | D5: 検疫・正式申告等（AUD1,000超や検査時のみ） | E5: バルキー2,520円、繁忙期割増34円(11/1〜12/31)
A6: 申告価値の上限 | B6: 1,300 USD | C6: £135（IOSS） | D6: AUD1,000/日・同一バイヤー | E6: €150（IOSS）
A7: 重量制限 | B7: 請求重量25kg以下（本土48州）／15kg以下（48州以外） | C7: 実重量15kg以下・請求重量25kg以下 | D7: 実重量22kg以下・請求重量22.5kg以下 | E7: 請求重量30kg以下（ドイツ25kg・スウェーデン20kg）
A8: 推定配送所要日数 | B8: 8〜12営業日（本土48州） | C8: 7〜10営業日 | D8: 6〜12営業日 | E8: 6〜16営業日
